Lython/ClassParser.py
Lython/Compiler.py
Lython/Console.py
Lython/Exception.py
Lython/Interpreter.py
Lython/Parser.py
Lython/Repl.py
Lython/__init__.py
Lython/util.py
programminglython-0.2.2.data/scripts/lython
programminglython-0.2.2.dist-info/METADATA
programminglython-0.2.2.dist-info/WHEEL
programminglython-0.2.2.dist-info/top_level.txt
programminglython-0.2.2.dist-info/RECORD
