Metadata-Version: 2.1
Name: programminglython
Version: 0.2.2
Summary: Lython programming language built on top of CPython
Home-page: https://github.com/guangrei/lython
Author: Guangrei
Author-email: myawn@pm.me
License: MIT
Platform: any
Requires-Dist: var-dump
